{
  "sheet_name": "COD",
  "total_rows": 28,
  "total_columns": 13,
  "columns": [
    "Site & PA$",
    "Time",
    "PA$",
    "Game Name",
    "Vanguard",
    "Per Level",
    "Per Range",
    "CW",
    "Per Level.1",
    "Per Range.1",
    "MW",
    "Per Level.2",
    "Per Range.2"
  ],
  "data": [
    {
      "Site & PA$": 15.0,
      "Time": 3.0,
      "PA$": 15.0,
      "Game Name": "Game: COD Vanguard",
      "Vanguard": "25-30",
      "Per Level": "2",
      "Per Range": 10.0,
      "CW": "25-30",
      "Per Level.1": "3",
      "Per Range.1": 15.0,
      "MW": "25-30",
      "Per Level.2": "5",
      "Per Range.2": 25.0
    },
    {
      "Site & PA$": 75.0,
      "Time": 10.0,
      "PA$": 75.0,
      "Game Name": "Game: COD Cold War",
      "Vanguard": "30-35",
      "Per Level": "2",
      "Per Range": 10.0,
      "CW": "30-35",
      "Per Level.1": "3",
      "Per Range.1": 15.0,
      "MW": "30-35",
      "Per Level.2": "5",
      "Per Range.2": 25.0
    },
    {
      "Site & PA$": 150.0,
      "Time": 24.0,
      "PA$": 150.0,
      "Game Name": "Game: COD Modern Warfare",
      "Vanguard": "35-40",
      "Per Level": "3",
      "Per Range": 15.0,
      "CW": "35-40",
      "Per Level.1": "3",
      "Per Range.1": 15.0,
      "MW": "35-40",
      "Per Level.2": "7",
      "Per Range.2": 35.0
    },
    {
      "Site & PA$": 20.0,
      "Time": "",
      "PA$": 20.0,
      "Game Name": "",
      "Vanguard": "65-70",
      "Per Level": "2",
      "Per Range": 10.0,
      "CW": "65-70",
      "Per Level.1": "2",
      "Per Range.1": 10.0,
      "MW": "65-70",
      "Per Level.2": "2",
      "Per Range.2": 10.0
    },
    {
      "Site & PA$": 35.0,
      "Time": "",
      "PA$": 35.0,
      "Game Name": "",
      "Vanguard": "75-80",
      "Per Level": "2",
      "Per Range": 10.0,
      "CW": "75-80",
      "Per Level.1": "2",
      "Per Range.1": 10.0,
      "MW": "75-80",
      "Per Level.2": "2",
      "Per Range.2": 10.0
    },
    {
      "Site & PA$": 345.0,
      "Time": 240.0,
      "PA$": 345.0,
      "Game Name": "",
      "Vanguard": "110-115",
      "Per Level": "4",
      "Per Range": 20.0,
      "CW": "110-115",
      "Per Level.1": "4",
      "Per Range.1": 20.0,
      "MW": "110-115",
      "Per Level.2": "4",
      "Per Range.2": 20.0
    },
    {
      "Site & PA$": 450.0,
      "Time": 7.0,
      "PA$": 450.0,
      "Game Name": "",
      "Vanguard": "155-160",
      "Per Level": "0",
      "Per Range": "",
      "CW": "155-160",
      "Per Level.1": "0",
      "Per Range.1": "",
      "MW": "155-160",
      "Per Level.2": "0",
      "Per Range.2": ""
    },
    {
      "Site & PA$": 50.0,
      "Time": 12.0,
      "PA$": 50.0,
      "Game Name": "",
      "Vanguard": "195-200",
      "Per Level": "0",
      "Per Range": "",
      "CW": "195-200",
      "Per Level.1": "0",
      "Per Range.1": "",
      "MW": "195-200",
      "Per Level.2": "0",
      "Per Range.2": ""
    },
    {
      "Site & PA$": 169.0,
      "Time": 48.0,
      "PA$": 169.0,
      "Game Name": "",
      "Vanguard": "0",
      "Per Level": "211",
      "Per Range": "",
      "CW": "0",
      "Per Level.1": "514",
      "Per Range.1": "",
      "MW": "0",
      "Per Level.2": "655",
      "Per Range.2": ""
    },
    {
      "Site & PA$": 99.0,
      "Time": 24.0,
      "PA$": 99.0,
      "Game Name": "",
      "Vanguard": "1",
      "Per Level": "",
      "Per Range": "",
      "CW": "1",
      "Per Level.1": "",
      "Per Range.1": "",
      "MW": "1",
      "Per Level.2": "",
      "Per Range.2": ""
    },
    {
      "Site & PA$": 110.0,
      "Time": 48.0,
      "PA$": 110.0,
      "Game Name": "",
      "Vanguard": "Level",
      "Per Level": "Cumulative",
      "Per Range": "",
      "CW": "xxx",
      "Per Level.1": "Cumulative",
      "Per Range.1": "",
      "MW": "xxx",
      "Per Level.2": "Cumulative",
      "Per Range.2": ""
    },
    {
      "Site & PA$": 170.0,
      "Time": 48.0,
      "PA$": 170.0,
      "Game Name": "",
      "Vanguard": "1",
      "Per Level": "0",
      "Per Range": "",
      "CW": "1",
      "Per Level.1": "0",
      "Per Range.1": "",
      "MW": "1",
      "Per Level.2": "0",
      "Per Range.2": ""
    },
    {
      "Site & PA$": 80.0,
      "Time": 24.0,
      "PA$": 80.0,
      "Game Name": "",
      "Vanguard": "2",
      "Per Level": "2",
      "Per Range": "",
      "CW": "2",
      "Per Level.1": "1",
      "Per Range.1": "",
      "MW": "2",
      "Per Level.2": "5",
      "Per Range.2": ""
    },
    {
      "Site & PA$": 55.0,
      "Time": 1.0,
      "PA$": 55.0,
      "Game Name": "",
      "Vanguard": "8",
      "Per Level": "14",
      "Per Range": "",
      "CW": "8",
      "Per Level.1": "7",
      "Per Range.1": "",
      "MW": "8",
      "Per Level.2": "35",
      "Per Range.2": ""
    },
    {
      "Site & PA$": 80.0,
      "Time": 2.0,
      "PA$": 80.0,
      "Game Name": "",
      "Vanguard": "17",
      "Per Level": "32",
      "Per Range": "",
      "CW": "17",
      "Per Level.1": "30",
      "Per Range.1": "",
      "MW": "17",
      "Per Level.2": "80",
      "Per Range.2": ""
    },
    {
      "Site & PA$": 140.0,
      "Time": 3.0,
      "PA$": 140.0,
      "Game Name": "",
      "Vanguard": "18",
      "Per Level": "34",
      "Per Range": "",
      "CW": "18",
      "Per Level.1": "33",
      "Per Range.1": "",
      "MW": "18",
      "Per Level.2": "85",
      "Per Range.2": ""
    },
    {
      "Site & PA$": 300.0,
      "Time": 7.0,
      "PA$": 300.0,
      "Game Name": "",
      "Vanguard": "20",
      "Per Level": "38",
      "Per Range": "",
      "CW": "20",
      "Per Level.1": "39",
      "Per Range.1": "",
      "MW": "20",
      "Per Level.2": "95",
      "Per Range.2": ""
    },
    {
      "Site & PA$": 400.0,
      "Time": 10.0,
      "PA$": 400.0,
      "Game Name": "",
      "Vanguard": "21",
      "Per Level": "40",
      "Per Range": "",
      "CW": "21",
      "Per Level.1": "42",
      "Per Range.1": "",
      "MW": "21",
      "Per Level.2": "100",
      "Per Range.2": ""
    },
    {
      "Site & PA$": 1450.0,
      "Time": 22.0,
      "PA$": 1450.0,
      "Game Name": "",
      "Vanguard": "23",
      "Per Level": "44",
      "Per Range": "",
      "CW": "23",
      "Per Level.1": "48",
      "Per Range.1": "",
      "MW": "23",
      "Per Level.2": "110",
      "Per Range.2": ""
    },
    {
      "Site & PA$": 1800.0,
      "Time": 34.0,
      "PA$": 1800.0,
      "Game Name": "",
      "Vanguard": "24",
      "Per Level": "46",
      "Per Range": "",
      "CW": "24",
      "Per Level.1": "51",
      "Per Range.1": "",
      "MW": "24",
      "Per Level.2": "115",
      "Per Range.2": ""
    },
    {
      "Site & PA$": 310.0,
      "Time": 48.0,
      "PA$": 310.0,
      "Game Name": "",
      "Vanguard": "30",
      "Per Level": "58",
      "Per Range": "",
      "CW": "30",
      "Per Level.1": "69",
      "Per Range.1": "",
      "MW": "30",
      "Per Level.2": "145",
      "Per Range.2": ""
    },
    {
      "Site & PA$": 345.0,
      "Time": 24.0,
      "PA$": 345.0,
      "Game Name": "",
      "Vanguard": "31",
      "Per Level": "60",
      "Per Range": "",
      "CW": "31",
      "Per Level.1": "72",
      "Per Range.1": "",
      "MW": "31",
      "Per Level.2": "150",
      "Per Range.2": ""
    },
    {
      "Site & PA$": 75.0,
      "Time": 1.0,
      "PA$": 75.0,
      "Game Name": "",
      "Vanguard": "41",
      "Per Level": "87",
      "Per Range": "",
      "CW": "41",
      "Per Level.1": "103",
      "Per Range.1": "",
      "MW": "41",
      "Per Level.2": "212",
      "Per Range.2": ""
    },
    {
      "Site & PA$": 100.0,
      "Time": 2.0,
      "PA$": 100.0,
      "Game Name": "",
      "Vanguard": "42",
      "Per Level": "91",
      "Per Range": "",
      "CW": "42",
      "Per Level.1": "107",
      "Per Range.1": "",
      "MW": "42",
      "Per Level.2": "219",
      "Per Range.2": ""
    },
    {
      "Site & PA$": 250.0,
      "Time": 5.0,
      "PA$": 250.0,
      "Game Name": "",
      "Vanguard": "43",
      "Per Level": "95",
      "Per Range": "",
      "CW": "43",
      "Per Level.1": "111",
      "Per Range.1": "",
      "MW": "43",
      "Per Level.2": "226",
      "Per Range.2": ""
    },
    {
      "Site & PA$": 1650.0,
      "Time": 20.0,
      "PA$": 1650.0,
      "Game Name": "",
      "Vanguard": "44",
      "Per Level": "99",
      "Per Range": "",
      "CW": "44",
      "Per Level.1": "115",
      "Per Range.1": "",
      "MW": "44",
      "Per Level.2": "233",
      "Per Range.2": ""
    },
    {
      "Site & PA$": 100.0,
      "Time": 1.0,
      "PA$": 100.0,
      "Game Name": "",
      "Vanguard": "50",
      "Per Level": "128",
      "Per Range": "",
      "CW": "50",
      "Per Level.1": "144",
      "Per Range.1": "",
      "MW": "50",
      "Per Level.2": "275",
      "Per Range.2": ""
    },
    {
      "Site & PA$": 60.0,
      "Time": 24.0,
      "PA$": 60.0,
      "Game Name": "",
      "Vanguard": "51",
      "Per Level": "133",
      "Per Range": "",
      "CW": "51",
      "Per Level.1": "149",
      "Per Range.1": "",
      "MW": "51",
      "Per Level.2": "282",
      "Per Range.2": ""
    }
  ]
}